{"businesses": [{"id": "TY68GixhXgHuEXYzzx6KSw", "alias": "bourbon-street-bar-and-grille-new-york", "name": "Bourbon Street Bar & Grille", "image_url": "https://s3-media1.fl.yelpcdn.com/bphoto/PDfGL5_xtSdoK1rKwyWDMQ/o.jpg", "is_closed": false, "url": "https://www.yelp.com/biz/bourbon-street-bar-and-grille-new-york?adjust_creative=Vw2ZAYX48yvF8qP0CjwWnw&utm_campaign=yelp_api_v3&utm_medium=api_v3_business_search&utm_source=Vw2ZAYX48yvF8qP0CjwWnw", "review_count": 824, "categories": [{"alias": "cajun", "title": "Cajun/Creole"}, {"alias": "southern", "title": "Southern"}], "rating": 3.5, "coordinates": {"latitude": 40.7603187561035, "longitude": -73.9897842407227}, "transactions": ["restaurant_reservation", "pickup", "delivery"], "price": "$$", "location": {"address1": "346 W 46th St", "address2": "", "address3": "", "city": "New York", "zip_code": "10036", "country": "US", "state": "NY", "display_address": ["346 W 46th St", "New York, NY 10036"]}, "phone": "+12122452030", "display_phone": "(212) 245-2030", "distance": 950.2974511687347}, {"id": "ESREfCxyY9A1Wetnk47xJQ", "alias": "dukes-new-york-9", "name": "Duke's", "image_url": "https://s3-media4.fl.yelpcdn.com/bphoto/zheBaz5IO9wxl8b-CU_Kcg/o.jpg", "is_closed": false, "url": "https://www.yelp.com/biz/dukes-new-york-9?adjust_creative=Vw2ZAYX48yvF8qP0CjwWnw&utm_campaign=yelp_api_v3&utm_medium=api_v3_business_search&utm_source=Vw2ZAYX48yvF8qP0CjwWnw", "review_count": 769, "categories": [{"alias": "southern", "title": "Southern"}, {"alias": "tradamerican", "title": "American (Traditional)"}, {"alias": "bars", "title": "Bars"}], "rating": 3.5, "coordinates": {"latitude": 40.748089, "longitude": -73.976864}, "transactions": ["pickup", "delivery"], "price": "$$", "location": {"address1": "560 3rd Ave", "address2": "", "address3": "", "city": "New York", "zip_code": "10016", "country": "US", "state": "NY", "display_address": ["560 3rd Ave", "New York, NY 10016"]}, "phone": "+12129495400", "display_phone": "(212) 949-5400", "distance": 1355.3650483030556}, {"id": "Bjv99EWQdyJUGzAZYQ_WOA", "alias": "bubba-gump-shrimp-co-new-york-3", "name": "Bubba Gump Shrimp Co.", "image_url": "https://s3-media2.fl.yelpcdn.com/bphoto/YmaEBikjAPakrKQ4vQSUiQ/o.jpg", "is_closed": false, "url": "https://www.yelp.com/biz/bubba-gump-shrimp-co-new-york-3?adjust_creative=Vw2ZAYX48yvF8qP0CjwWnw&utm_campaign=yelp_api_v3&utm_medium=api_v3_business_search&utm_source=Vw2ZAYX48yvF8qP0CjwWnw", "review_count": 952, "categories": [{"alias": "seafood", "title": "Seafood"}, {"alias": "southern", "title": "Southern"}, {"alias": "cajun", "title": "Cajun/Creole"}], "rating": 3.5, "coordinates": {"latitude": 40.757194, "longitude": -73.9864036}, "transactions": [], "price": "$$", "location": {"address1": "1501 Broadway", "address2": null, "address3": "", "city": "New York", "zip_code": "10036", "country": "US", "state": "NY", "display_address": ["1501 Broadway", "New York, NY 10036"]}, "phone": "+12123917100", "display_phone": "(212) 391-7100", "distance": 745.6126764917569}, {"id": "lApqVlBw5SMvV_nJwHlPvQ", "alias": "hill-country-chicken-new-york", "name": "Hill Country Chicken", "image_url": "https://s3-media4.fl.yelpcdn.com/bphoto/o_xEaVWPLJJJssJbxF9sWg/o.jpg", "is_closed": false, "url": "https://www.yelp.com/biz/hill-country-chicken-new-york?adjust_creative=Vw2ZAYX48yvF8qP0CjwWnw&utm_campaign=yelp_api_v3&utm_medium=api_v3_business_search&utm_source=Vw2ZAYX48yvF8qP0CjwWnw", "review_count": 1107, "categories": [{"alias": "southern", "title": "Southern"}, {"alias": "soulfood", "title": "Soul Food"}, {"alias": "tradamerican", "title": "American (Traditional)"}], "rating": 3.5, "coordinates": {"latitude": 40.74332, "longitude": -73.98924}, "transactions": ["pickup", "delivery"], "price": "$$", "location": {"address1": "1123 Broadway", "address2": "", "address3": "", "city": "New York", "zip_code": "10010", "country": "US", "state": "NY", "display_address": ["1123 Broadway", "New York, NY 10010"]}, "phone": "+12122576446", "display_phone": "(212) 257-6446", "distance": 2084.0133658847076}, {"id": "Wdt-exLSaHXQRH7V_7-VVg", "alias": "spoonfed-nyc-new-york", "name": "Spoonfed NYC", "image_url": "https://s3-media3.fl.yelpcdn.com/bphoto/xxz6vpSY12D3TuAhXhSbvQ/o.jpg", "is_closed": false, "url": "https://www.yelp.com/biz/spoonfed-nyc-new-york?adjust_creative=Vw2ZAYX48yvF8qP0CjwWnw&utm_campaign=yelp_api_v3&utm_medium=api_v3_business_search&utm_source=Vw2ZAYX48yvF8qP0CjwWnw", "review_count": 340, "categories": [{"alias": "soulfood", "title": "Soul Food"}, {"alias": "southern", "title": "Southern"}], "rating": 4.0, "coordinates": {"latitude": 40.7636295, "longitude": -73.9868805}, "transactions": ["restaurant_reservation", "pickup", "delivery"], "price": "$$", "location": {"address1": "331 W 51st St", "address2": "", "address3": "", "city": "New York", "zip_code": "10019", "country": "US", "state": "NY", "display_address": ["331 W 51st St", "New York, NY 10019"]}, "phone": "+16463681854", "display_phone": "(646) 368-1854", "distance": 801.4389421826849}, {"id": "4KHjnRNvrkKHchEznhlnSA", "alias": "sweet-chick-brooklyn", "name": "Sweet Chick", "image_url": "https://s3-media3.fl.yelpcdn.com/bphoto/-B7HnMZQQh1MemYmypaJ0Q/o.jpg", "is_closed": false, "url": "https://www.yelp.com/biz/sweet-chick-brooklyn?adjust_creative=Vw2ZAYX48yvF8qP0CjwWnw&utm_campaign=yelp_api_v3&utm_medium=api_v3_business_search&utm_source=Vw2ZAYX48yvF8qP0CjwWnw", "review_count": 1802, "categories": [{"alias": "southern", "title": "Southern"}, {"alias": "breakfast_brunch", "title": "Breakfast & Brunch"}, {"alias": "tradamerican", "title": "American (Traditional)"}], "rating": 4.0, "coordinates": {"latitude": 40.718423, "longitude": -73.9574279}, "transactions": [], "price": "$$", "location": {"address1": "164 Bedford Ave", "address2": "", "address3": "", "city": "Brooklyn", "zip_code": "11211", "country": "US", "state": "NY", "display_address": ["164 Bedford Ave", "Brooklyn, NY 11211"]}, "phone": "+13477254793", "display_phone": "(347) 725-4793", "distance": 4974.631505727091}, {"id": "4zBGXDXg9DzK0IROwCUeFg", "alias": "cowgirl-seahorse-new-york-2", "name": "Cowgirl Seahorse", "image_url": "https://s3-media4.fl.yelpcdn.com/bphoto/mRCV94yIU3zkKiL6FPR6Vg/o.jpg", "is_closed": false, "url": "https://www.yelp.com/biz/cowgirl-seahorse-new-york-2?adjust_creative=Vw2ZAYX48yvF8qP0CjwWnw&utm_campaign=yelp_api_v3&utm_medium=api_v3_business_search&utm_source=Vw2ZAYX48yvF8qP0CjwWnw", "review_count": 546, "categories": [{"alias": "tex-mex", "title": "Tex-Mex"}, {"alias": "seafood", "title": "Seafood"}, {"alias": "southern", "title": "Southern"}], "rating": 4.0, "coordinates": {"latitude": 40.7081358, "longitude": -74.0004532}, "transactions": ["pickup", "delivery"], "price": "$$", "location": {"address1": "259 Front St", "address2": "", "address3": "", "city": "New York", "zip_code": "10038", "country": "US", "state": "NY", "display_address": ["259 Front St", "New York, NY 10038"]}, "phone": "+12126087873", "display_phone": "(212) 608-7873", "distance": 6079.1587902381925}, {"id": "tA1QO_GParSsaOaO8UoBvQ", "alias": "blue-smoke-new-york-4", "name": "Blue Smoke", "image_url": "https://s3-media1.fl.yelpcdn.com/bphoto/y_o53DqH1s_4kHnjklHmzg/o.jpg", "is_closed": false, "url": "https://www.yelp.com/biz/blue-smoke-new-york-4?adjust_creative=Vw2ZAYX48yvF8qP0CjwWnw&utm_campaign=yelp_api_v3&utm_medium=api_v3_business_search&utm_source=Vw2ZAYX48yvF8qP0CjwWnw", "review_count": 592, "categories": [{"alias": "southern", "title": "Southern"}, {"alias": "bbq", "title": "Barbeque"}, {"alias": "sportsbars", "title": "Sports Bars"}], "rating": 3.5, "coordinates": {"latitude": 40.714486, "longitude": -74.0152768}, "transactions": ["pickup", "delivery"], "price": "$$", "location": {"address1": "255 Vesey St", "address2": "", "address3": "", "city": "New York", "zip_code": "10282", "country": "US", "state": "NY", "display_address": ["255 Vesey St", "New York, NY 10282"]}, "phone": "+12128892005", "display_phone": "(212) 889-2005", "distance": 5905.028596717877}, {"id": "j9TdOBSQ1LRw8v3hW5fObQ", "alias": "pies-n-thighs-brooklyn", "name": "Pies-n-Thighs", "image_url": "https://s3-media3.fl.yelpcdn.com/bphoto/ZEox6v_ipIvcrzeRv9mFIA/o.jpg", "is_closed": false, "url": "https://www.yelp.com/biz/pies-n-thighs-brooklyn?adjust_creative=Vw2ZAYX48yvF8qP0CjwWnw&utm_campaign=yelp_api_v3&utm_medium=api_v3_business_search&utm_source=Vw2ZAYX48yvF8qP0CjwWnw", "review_count": 2700, "categories": [{"alias": "southern", "title": "Southern"}, {"alias": "bbq", "title": "Barbeque"}, {"alias": "breakfast_brunch", "title": "Breakfast & Brunch"}], "rating": 4.0, "coordinates": {"latitude": 40.711191, "longitude": -73.961424}, "transactions": ["pickup", "delivery"], "price": "$$", "location": {"address1": "166 S 4th St", "address2": null, "address3": "", "city": "Brooklyn", "zip_code": "11211", "country": "US", "state": "NY", "display_address": ["166 S 4th St", "Brooklyn, NY 11211"]}, "phone": "+13475296090", "display_phone": "(347) 529-6090", "distance": 5637.881023100139}, {"id": "ZV-sZmRF-4Zye_lJlVCtVg", "alias": "southern-hospitality-bbq-new-york-2", "name": "Southern Hospitality BBQ", "image_url": "https://s3-media3.fl.yelpcdn.com/bphoto/f2H0zfwgcFjChbwWE_XusQ/o.jpg", "is_closed": false, "url": "https://www.yelp.com/biz/southern-hospitality-bbq-new-york-2?adjust_creative=Vw2ZAYX48yvF8qP0CjwWnw&utm_campaign=yelp_api_v3&utm_medium=api_v3_business_search&utm_source=Vw2ZAYX48yvF8qP0CjwWnw", "review_count": 1241, "categories": [{"alias": "southern", "title": "Southern"}, {"alias": "bbq", "title": "Barbeque"}, {"alias": "sandwiches", "title": "Sandwiches"}], "rating": 3.0, "coordinates": {"latitude": 40.76053, "longitude": -73.99133}, "transactions": ["pickup", "delivery"], "price": "$$", "location": {"address1": "645 9th Ave", "address2": "", "address3": "", "city": "New York", "zip_code": "10036", "country": "US", "state": "NY", "display_address": ["645 9th Ave", "New York, NY 10036"]}, "phone": "+12122651000", "display_phone": "(212) 265-1000", "distance": 1087.2630699065157}, {"id": "8G6H30Krmj8-OHs6hZfT1g", "alias": "belle-harlem-new-york", "name": "Belle Harlem", "image_url": "https://s3-media1.fl.yelpcdn.com/bphoto/__BxtpE6a7wNxGWOsn75rQ/o.jpg", "is_closed": false, "url": "https://www.yelp.com/biz/belle-harlem-new-york?adjust_creative=Vw2ZAYX48yvF8qP0CjwWnw&utm_campaign=yelp_api_v3&utm_medium=api_v3_business_search&utm_source=Vw2ZAYX48yvF8qP0CjwWnw", "review_count": 121, "categories": [{"alias": "newamerican", "title": "American (New)"}, {"alias": "southern", "title": "Southern"}, {"alias": "comfortfood", "title": "Comfort Food"}], "rating": 4.5, "coordinates": {"latitude": 40.8173, "longitude": -73.94171}, "transactions": [], "price": "$$$", "location": {"address1": "2363 Adam Clayton Powell Blvd", "address2": null, "address3": "", "city": "New York", "zip_code": "10030", "country": "US", "state": "NY", "display_address": ["2363 Adam Clayton Powell Blvd", "New York, NY 10030"]}, "phone": "+13478194076", "display_phone": "(347) 819-4076", "distance": 7065.766844871299}, {"id": "2hmhZim4bX2lbjPSNc7LaA", "alias": "javelina-new-york", "name": "Javelina", "image_url": "https://s3-media3.fl.yelpcdn.com/bphoto/cjFxBfgfv3mlVvAibs_69A/o.jpg", "is_closed": false, "url": "https://www.yelp.com/biz/javelina-new-york?adjust_creative=Vw2ZAYX48yvF8qP0CjwWnw&utm_campaign=yelp_api_v3&utm_medium=api_v3_business_search&utm_source=Vw2ZAYX48yvF8qP0CjwWnw", "review_count": 421, "categories": [{"alias": "tex-mex", "title": "Tex-Mex"}, {"alias": "southern", "title": "Southern"}, {"alias": "mexican", "title": "Mexican"}], "rating": 3.5, "coordinates": {"latitude": 40.7368812561035, "longitude": -73.9873886108398}, "transactions": ["pickup", "delivery"], "price": "$$", "location": {"address1": "119 E 18th St", "address2": null, "address3": "", "city": "New York", "zip_code": "10003", "country": "US", "state": "NY", "display_address": ["119 E 18th St", "New York, NY 10003"]}, "phone": "+12125390202", "display_phone": "(212) 539-0202", "distance": 2703.4094470990285}, {"id": "kSI-wgcYYfpcHcgDrbKIfg", "alias": "sugar-freak-astoria", "name": "Sugar Freak", "image_url": "https://s3-media1.fl.yelpcdn.com/bphoto/E8BfaEz5SttZaBwPy7XegQ/o.jpg", "is_closed": false, "url": "https://www.yelp.com/biz/sugar-freak-astoria?adjust_creative=Vw2ZAYX48yvF8qP0CjwWnw&utm_campaign=yelp_api_v3&utm_medium=api_v3_business_search&utm_source=Vw2ZAYX48yvF8qP0CjwWnw", "review_count": 1565, "categories": [{"alias": "cajun", "title": "Cajun/Creole"}, {"alias": "southern", "title": "Southern"}, {"alias": "breakfast_brunch", "title": "Breakfast & Brunch"}], "rating": 4.0, "coordinates": {"latitude": 40.7646298318085, "longitude": -73.9159499108791}, "transactions": ["pickup", "delivery"], "price": "$$", "location": {"address1": "37-11 30th Ave", "address2": "", "address3": "", "city": "Astoria", "zip_code": "11103", "country": "US", "state": "NY", "display_address": ["37-11 30th Ave", "Astoria, NY 11103"]}, "phone": "+17186061900", "display_phone": "(718) 606-1900", "distance": 5290.920200046322}, {"id": "s33HF6gGTWo3D7QxBMv9ow", "alias": "cowgirl-new-york", "name": "Cowgirl", "image_url": "https://s3-media3.fl.yelpcdn.com/bphoto/gK5sSrPWBvQAtO1TzXp8Aw/o.jpg", "is_closed": false, "url": "https://www.yelp.com/biz/cowgirl-new-york?adjust_creative=Vw2ZAYX48yvF8qP0CjwWnw&utm_campaign=yelp_api_v3&utm_medium=api_v3_business_search&utm_source=Vw2ZAYX48yvF8qP0CjwWnw", "review_count": 556, "categories": [{"alias": "southern", "title": "Southern"}, {"alias": "cocktailbars", "title": "Cocktail Bars"}], "rating": 3.5, "coordinates": {"latitude": 40.733805, "longitude": -74.006488}, "transactions": ["pickup", "delivery"], "price": "$$", "location": {"address1": "519 Hudson St", "address2": "", "address3": "", "city": "New York", "zip_code": "10014", "country": "US", "state": "NY", "display_address": ["519 Hudson St", "New York, NY 10014"]}, "phone": "+12126331133", "display_phone": "(212) 633-1133", "distance": 3765.988783320942}, {"id": "H4fS32597GN025rMM85W-g", "alias": "sisters-caribbean-cuisine-new-york", "name": "Sisters' Caribbean Cuisine", "image_url": "https://s3-media3.fl.yelpcdn.com/bphoto/s2onSwYdrYJ8-9duIZYgrA/o.jpg", "is_closed": false, "url": "https://www.yelp.com/biz/sisters-caribbean-cuisine-new-york?adjust_creative=Vw2ZAYX48yvF8qP0CjwWnw&utm_campaign=yelp_api_v3&utm_medium=api_v3_business_search&utm_source=Vw2ZAYX48yvF8qP0CjwWnw", "review_count": 142, "categories": [{"alias": "caribbean", "title": "Caribbean"}, {"alias": "southern", "title": "Southern"}, {"alias": "soulfood", "title": "Soul Food"}], "rating": 4.0, "coordinates": {"latitude": 40.80503, "longitude": -73.94082}, "transactions": ["pickup", "delivery"], "price": "$$", "location": {"address1": "47 E 124th St", "address2": "", "address3": "", "city": "New York", "zip_code": "10035", "country": "US", "state": "NY", "display_address": ["47 E 124th St", "New York, NY 10035"]}, "phone": "+12124103000", "display_phone": "(212) 410-3000", "distance": 5915.389908393065}, {"id": "_fLkAgigkhOnzZMj7uHZ1A", "alias": "brother-jimmys-bbq-new-york-2", "name": "Brother Jimmy's BBQ", "image_url": "https://s3-media4.fl.yelpcdn.com/bphoto/Y3cDzpgXZIHrbR00MtMroQ/o.jpg", "is_closed": false, "url": "https://www.yelp.com/biz/brother-jimmys-bbq-new-york-2?adjust_creative=Vw2ZAYX48yvF8qP0CjwWnw&utm_campaign=yelp_api_v3&utm_medium=api_v3_business_search&utm_source=Vw2ZAYX48yvF8qP0CjwWnw", "review_count": 565, "categories": [{"alias": "bbq", "title": "Barbeque"}, {"alias": "southern", "title": "Southern"}, {"alias": "burgers", "title": "Burgers"}], "rating": 3.0, "coordinates": {"latitude": 40.7500749013242, "longitude": -73.9947574524591}, "transactions": ["pickup", "delivery"], "price": "$$", "location": {"address1": "416 8th Ave", "address2": "", "address3": "", "city": "New York", "zip_code": "10021", "country": "US", "state": "NY", "display_address": ["416 8th Ave", "New York, NY 10021"]}, "phone": "+12129677603", "display_phone": "(212) 967-7603", "distance": 1773.8106139653207}, {"id": "hsml8TmJ3puTw1HnzZj-Rg", "alias": "brother-jimmys-bbq-new-york-4", "name": "Brother Jimmy's BBQ", "image_url": "https://s3-media3.fl.yelpcdn.com/bphoto/VqpE8N93cKZImdotki6rhg/o.jpg", "is_closed": false, "url": "https://www.yelp.com/biz/brother-jimmys-bbq-new-york-4?adjust_creative=Vw2ZAYX48yvF8qP0CjwWnw&utm_campaign=yelp_api_v3&utm_medium=api_v3_business_search&utm_source=Vw2ZAYX48yvF8qP0CjwWnw", "review_count": 459, "categories": [{"alias": "bbq", "title": "Barbeque"}, {"alias": "bars", "title": "Bars"}, {"alias": "southern", "title": "Southern"}], "rating": 3.0, "coordinates": {"latitude": 40.7445101402263, "longitude": -73.980771217791}, "transactions": ["pickup", "delivery"], "price": "$$", "location": {"address1": "181 Lexington Ave", "address2": "", "address3": "", "city": "New York", "zip_code": "10016", "country": "US", "state": "NY", "display_address": ["181 Lexington Ave", "New York, NY 10016"]}, "phone": "+12127797427", "display_phone": "(212) 779-7427", "distance": 1756.7339704834512}, {"id": "4GYc1Ld8r4rGQJKz_Qp07A", "alias": "miss-mamies-spoonbread-too-new-york", "name": "Miss Mamie's Spoonbread Too", "image_url": "https://s3-media4.fl.yelpcdn.com/bphoto/MbWh7EKf6kUvHdwgoljULw/o.jpg", "is_closed": false, "url": "https://www.yelp.com/biz/miss-mamies-spoonbread-too-new-york?adjust_creative=Vw2ZAYX48yvF8qP0CjwWnw&utm_campaign=yelp_api_v3&utm_medium=api_v3_business_search&utm_source=Vw2ZAYX48yvF8qP0CjwWnw", "review_count": 393, "categories": [{"alias": "southern", "title": "Southern"}, {"alias": "bbq", "title": "Barbeque"}, {"alias": "soulfood", "title": "Soul Food"}], "rating": 3.0, "coordinates": {"latitude": 40.801462, "longitude": -73.960859}, "transactions": ["pickup", "delivery"], "price": "$$", "location": {"address1": "366 W 110th St", "address2": "", "address3": "", "city": "New York", "zip_code": "10025", "country": "US", "state": "NY", "display_address": ["366 W 110th St", "New York, NY 10025"]}, "phone": "+12128656744", "display_phone": "(212) 865-6744", "distance": 4820.991753606352}, {"id": "7zxV9U7_SJ1npeLCkHUzjg", "alias": "yankee-doodle-dandys-new-york-2", "name": "Yankee Doodle Dandy's", "image_url": "https://s3-media4.fl.yelpcdn.com/bphoto/BLG5hynjc_qOtrCjhCQ6_A/o.jpg", "is_closed": false, "url": "https://www.yelp.com/biz/yankee-doodle-dandys-new-york-2?adjust_creative=Vw2ZAYX48yvF8qP0CjwWnw&utm_campaign=yelp_api_v3&utm_medium=api_v3_business_search&utm_source=Vw2ZAYX48yvF8qP0CjwWnw", "review_count": 105, "categories": [{"alias": "foodtrucks", "title": "Food Trucks"}, {"alias": "southern", "title": "Southern"}, {"alias": "newamerican", "title": "American (New)"}], "rating": 4.0, "coordinates": {"latitude": 40.71424, "longitude": -74.00642}, "transactions": ["pickup", "delivery"], "price": "$", "location": {"address1": null, "address2": null, "address3": "", "city": "New York", "zip_code": "11121", "country": "US", "state": "NY", "display_address": ["New York, NY 11121"]}, "phone": "+19732023130", "display_phone": "(973) 202-3130", "distance": 5760.5329072084705}, {"id": "MW04QetT-HjxF0tYEhiG0g", "alias": "capt-loui-new-york", "name": "Cap't Loui", "image_url": "https://s3-media4.fl.yelpcdn.com/bphoto/jdoGIcWH7H1Ded8EBUfCzg/o.jpg", "is_closed": false, "url": "https://www.yelp.com/biz/capt-loui-new-york?adjust_creative=Vw2ZAYX48yvF8qP0CjwWnw&utm_campaign=yelp_api_v3&utm_medium=api_v3_business_search&utm_source=Vw2ZAYX48yvF8qP0CjwWnw", "review_count": 114, "categories": [{"alias": "cajun", "title": "Cajun/Creole"}, {"alias": "seafood", "title": "Seafood"}, {"alias": "southern", "title": "Southern"}], "rating": 4.0, "coordinates": {"latitude": 40.81431, "longitude": -73.9598}, "transactions": ["pickup", "delivery"], "price": "$$", "location": {"address1": "3147 Broadway", "address2": null, "address3": "", "city": "New York", "zip_code": "10027", "country": "US", "state": "NY", "display_address": ["3147 Broadway", "New York, NY 10027"]}, "phone": "+12122226608", "display_phone": "(212) 222-6608", "distance": 6217.269295174836}, {"id": "jFgLOxswrUC_c-iqMjBLyQ", "alias": "ginnys-supper-club-new-york", "name": "Ginny's Supper Club", "image_url": "https://s3-media2.fl.yelpcdn.com/bphoto/ewL5sBaNowziLldaZbK7PA/o.jpg", "is_closed": false, "url": "https://www.yelp.com/biz/ginnys-supper-club-new-york?adjust_creative=Vw2ZAYX48yvF8qP0CjwWnw&utm_campaign=yelp_api_v3&utm_medium=api_v3_business_search&utm_source=Vw2ZAYX48yvF8qP0CjwWnw", "review_count": 160, "categories": [{"alias": "southern", "title": "Southern"}, {"alias": "jazzandblues", "title": "Jazz & Blues"}, {"alias": "diners", "title": "Diners"}], "rating": 3.5, "coordinates": {"latitude": 40.80815, "longitude": -73.94488}, "transactions": [], "price": "$$$", "location": {"address1": "310 Lenox Ave", "address2": "", "address3": "", "city": "New York", "zip_code": "10027", "country": "US", "state": "NY", "display_address": ["310 Lenox Ave", "New York, NY 10027"]}, "phone": "+12124213821", "display_phone": "(212) 421-3821", "distance": 6024.6201892795}, {"id": "cSg6wIFrYz_iYddUSV4BVw", "alias": "delimarie-new-york-2", "name": "Delimarie", "image_url": "https://s3-media1.fl.yelpcdn.com/bphoto/79Ss0Y1YLYHeFtEK6Kt9Dg/o.jpg", "is_closed": false, "url": "https://www.yelp.com/biz/delimarie-new-york-2?adjust_creative=Vw2ZAYX48yvF8qP0CjwWnw&utm_campaign=yelp_api_v3&utm_medium=api_v3_business_search&utm_source=Vw2ZAYX48yvF8qP0CjwWnw", "review_count": 99, "categories": [{"alias": "delis", "title": "Delis"}, {"alias": "southern", "title": "Southern"}, {"alias": "breakfast_brunch", "title": "Breakfast & Brunch"}], "rating": 4.0, "coordinates": {"latitude": 40.71541, "longitude": -74.00637}, "transactions": [], "price": "$", "location": {"address1": "106 Duane St", "address2": "", "address3": "", "city": "New York", "zip_code": "10007", "country": "US", "state": "NY", "display_address": ["106 Duane St", "New York, NY 10007"]}, "phone": "+12123496902", "display_phone": "(212) 349-6902", "distance": 5510.91152344397}, {"id": "NcHnZbq06y9llCt6ayf_Jw", "alias": "sweet-chick-long-island-city", "name": "Sweet Chick", "image_url": "https://s3-media2.fl.yelpcdn.com/bphoto/nqo1896TuI-xW-m0ccf4VA/o.jpg", "is_closed": false, "url": "https://www.yelp.com/biz/sweet-chick-long-island-city?adjust_creative=Vw2ZAYX48yvF8qP0CjwWnw&utm_campaign=yelp_api_v3&utm_medium=api_v3_business_search&utm_source=Vw2ZAYX48yvF8qP0CjwWnw", "review_count": 215, "categories": [{"alias": "southern", "title": "Southern"}, {"alias": "tradamerican", "title": "American (Traditional)"}, {"alias": "breakfast_brunch", "title": "Breakfast & Brunch"}], "rating": 4.0, "coordinates": {"latitude": 40.74578, "longitude": -73.95339}, "transactions": ["pickup", "restaurant_reservation", "delivery"], "price": "$$", "location": {"address1": "46-42 Vernon Blvd", "address2": "", "address3": null, "city": "Long Island City", "zip_code": "11101", "country": "US", "state": "NY", "display_address": ["46-42 Vernon Blvd", "Long Island City, NY 11101"]}, "phone": "+17184334064", "display_phone": "(718) 433-4064", "distance": 2660.840869299885}, {"id": "EE-HFgHfb-B3QdNFKhkUnA", "alias": "the-hog-pit-nyc-new-york", "name": "The Hog Pit NYC", "image_url": "https://s3-media2.fl.yelpcdn.com/bphoto/r2Z7-i3iajlURChYcLKY3w/o.jpg", "is_closed": false, "url": "https://www.yelp.com/biz/the-hog-pit-nyc-new-york?adjust_creative=Vw2ZAYX48yvF8qP0CjwWnw&utm_campaign=yelp_api_v3&utm_medium=api_v3_business_search&utm_source=Vw2ZAYX48yvF8qP0CjwWnw", "review_count": 234, "categories": [{"alias": "bbq", "title": "Barbeque"}, {"alias": "southern", "title": "Southern"}, {"alias": "bars", "title": "Bars"}], "rating": 3.0, "coordinates": {"latitude": 40.7445738, "longitude": -73.9904317}, "transactions": [], "price": "$$", "location": {"address1": "37B W 26th St", "address2": "", "address3": "", "city": "New York", "zip_code": "10010", "country": "US", "state": "NY", "display_address": ["37B W 26th St", "New York, NY 10010"]}, "phone": "+16467603645", "display_phone": "(646) 760-3645", "distance": 2008.7139061002317}, {"id": "GA5msU6NO9rQRctPfDJCBg", "alias": "peaches-hothouse-brooklyn", "name": "Peaches HotHouse", "image_url": "https://s3-media1.fl.yelpcdn.com/bphoto/KEAXgZGetzDf_pc4kse_mw/o.jpg", "is_closed": false, "url": "https://www.yelp.com/biz/peaches-hothouse-brooklyn?adjust_creative=Vw2ZAYX48yvF8qP0CjwWnw&utm_campaign=yelp_api_v3&utm_medium=api_v3_business_search&utm_source=Vw2ZAYX48yvF8qP0CjwWnw", "review_count": 1042, "categories": [{"alias": "southern", "title": "Southern"}, {"alias": "tradamerican", "title": "American (Traditional)"}, {"alias": "bars", "title": "Bars"}], "rating": 4.0, "coordinates": {"latitude": 40.6833699737169, "longitude": -73.9437798410654}, "transactions": ["pickup", "delivery"], "price": "$$", "location": {"address1": "415 Tompkins Ave", "address2": "", "address3": "", "city": "Brooklyn", "zip_code": "11216", "country": "US", "state": "NY", "display_address": ["415 Tompkins Ave", "Brooklyn, NY 11216"]}, "phone": "+17184839111", "display_phone": "(718) 483-9111", "distance": 9031.853322952038}, {"id": "jFYEsw6_4y4VMpSVB863sw", "alias": "mojave-astoria-2", "name": "Mojave", "image_url": "https://s3-media3.fl.yelpcdn.com/bphoto/5AS8pDB-WIPGJ3VpWXLNyw/o.jpg", "is_closed": false, "url": "https://www.yelp.com/biz/mojave-astoria-2?adjust_creative=Vw2ZAYX48yvF8qP0CjwWnw&utm_campaign=yelp_api_v3&utm_medium=api_v3_business_search&utm_source=Vw2ZAYX48yvF8qP0CjwWnw", "review_count": 670, "categories": [{"alias": "southern", "title": "Southern"}, {"alias": "mexican", "title": "Mexican"}, {"alias": "tex-mex", "title": "Tex-Mex"}], "rating": 3.5, "coordinates": {"latitude": 40.7753290076368, "longitude": -73.9119911693115}, "transactions": ["pickup", "delivery"], "price": "$$", "location": {"address1": "22-36 31st St", "address2": "", "address3": "", "city": "Astoria", "zip_code": "11105", "country": "US", "state": "NY", "display_address": ["22-36 31st St", "Astoria, NY 11105"]}, "phone": "+17185454100", "display_phone": "(718) 545-4100", "distance": 5847.758724577156}, {"id": "fAQVVgDt88mW739YJgKQdQ", "alias": "charlies-bar-and-kitchen-bronx", "name": "Charlie's Bar & Kitchen", "image_url": "https://s3-media1.fl.yelpcdn.com/bphoto/ACm-dMU44kFM-8PvCiS8vw/o.jpg", "is_closed": false, "url": "https://www.yelp.com/biz/charlies-bar-and-kitchen-bronx?adjust_creative=Vw2ZAYX48yvF8qP0CjwWnw&utm_campaign=yelp_api_v3&utm_medium=api_v3_business_search&utm_source=Vw2ZAYX48yvF8qP0CjwWnw", "review_count": 290, "categories": [{"alias": "cocktailbars", "title": "Cocktail Bars"}, {"alias": "southern", "title": "Southern"}, {"alias": "tradamerican", "title": "American (Traditional)"}], "rating": 4.0, "coordinates": {"latitude": 40.807874991887, "longitude": -73.9291545436554}, "transactions": ["pickup", "delivery"], "price": "$$", "location": {"address1": "112 Lincoln Ave", "address2": "", "address3": "", "city": "Bronx", "zip_code": "10454", "country": "US", "state": "NY", "display_address": ["112 Lincoln Ave", "Bronx, NY 10454"]}, "phone": "+17186842338", "display_phone": "(718) 684-2338", "distance": 6733.9592516927105}, {"id": "nnfJgt5uw7f-tx5HT09Bkw", "alias": "charles-pan-fried-chicken-restaurant-new-york", "name": "Charles Pan Fried Chicken Restaurant", "image_url": "https://s3-media2.fl.yelpcdn.com/bphoto/J6bfBEIMcJJM0lRXon4LlQ/o.jpg", "is_closed": false, "url": "https://www.yelp.com/biz/charles-pan-fried-chicken-restaurant-new-york?adjust_creative=Vw2ZAYX48yvF8qP0CjwWnw&utm_campaign=yelp_api_v3&utm_medium=api_v3_business_search&utm_source=Vw2ZAYX48yvF8qP0CjwWnw", "review_count": 74, "categories": [{"alias": "southern", "title": "Southern"}, {"alias": "chickenshop", "title": "Chicken Shop"}, {"alias": "soulfood", "title": "Soul Food"}], "rating": 4.0, "coordinates": {"latitude": 40.8146146267905, "longitude": -73.9482675120234}, "transactions": [], "price": "$$", "location": {"address1": "2461 Frederick Douglass Blvd", "address2": "", "address3": null, "city": "New York", "zip_code": "10027", "country": "US", "state": "NY", "display_address": ["2461 Frederick Douglass Blvd", "New York, NY 10027"]}, "phone": "+12122811800", "display_phone": "(212) 281-1800", "distance": 6562.662388871632}, {"id": "SBt2Y6JbBf3kWkz9ohPp0g", "alias": "brooklyn-bazaar-brooklyn", "name": "Brooklyn Bazaar", "image_url": "https://s3-media4.fl.yelpcdn.com/bphoto/WUiSn5G67eo-7iJBlPItJw/o.jpg", "is_closed": false, "url": "https://www.yelp.com/biz/brooklyn-bazaar-brooklyn?adjust_creative=Vw2ZAYX48yvF8qP0CjwWnw&utm_campaign=yelp_api_v3&utm_medium=api_v3_business_search&utm_source=Vw2ZAYX48yvF8qP0CjwWnw", "review_count": 232, "categories": [{"alias": "musicvenues", "title": "Music Venues"}, {"alias": "southern", "title": "Southern"}, {"alias": "karaoke", "title": "Karaoke"}], "rating": 3.5, "coordinates": {"latitude": 40.7301329064897, "longitude": -73.9547889981813}, "transactions": ["pickup", "delivery"], "price": "$$", "location": {"address1": "150 Greenpoint Ave", "address2": "", "address3": "", "city": "Brooklyn", "zip_code": "11222", "country": "US", "state": "NY", "display_address": ["150 Greenpoint Ave", "Brooklyn, NY 11222"]}, "phone": "", "display_phone": "", "distance": 3896.008932139387}, {"id": "vW7sMAxt4YcUS8tWONaX2g", "alias": "the-gumbo-bros-brooklyn", "name": "The Gumbo Bros", "image_url": "https://s3-media2.fl.yelpcdn.com/bphoto/39Mre72rxSoG-G8JdTM4ow/o.jpg", "is_closed": false, "url": "https://www.yelp.com/biz/the-gumbo-bros-brooklyn?adjust_creative=Vw2ZAYX48yvF8qP0CjwWnw&utm_campaign=yelp_api_v3&utm_medium=api_v3_business_search&utm_source=Vw2ZAYX48yvF8qP0CjwWnw", "review_count": 268, "categories": [{"alias": "cajun", "title": "Cajun/Creole"}, {"alias": "southern", "title": "Southern"}, {"alias": "sandwiches", "title": "Sandwiches"}], "rating": 4.5, "coordinates": {"latitude": 40.68925, "longitude": -73.9918}, "transactions": ["pickup", "delivery"], "price": "$$", "location": {"address1": "224 Atlantic Ave", "address2": "", "address3": null, "city": "Brooklyn", "zip_code": "11201", "country": "US", "state": "NY", "display_address": ["224 Atlantic Ave", "Brooklyn, NY 11201"]}, "phone": "+19179091471", "display_phone": "(917) 909-1471", "distance": 7969.821449523256}, {"id": "YARIb8L3uOo3fECJP2Pjlg", "alias": "slide-bar-b-q-maspeth", "name": "Slide Bar-B-Q", "image_url": "https://s3-media2.fl.yelpcdn.com/bphoto/Nf4ziShHN0tshvnQp3WWrg/o.jpg", "is_closed": false, "url": "https://www.yelp.com/biz/slide-bar-b-q-maspeth?adjust_creative=Vw2ZAYX48yvF8qP0CjwWnw&utm_campaign=yelp_api_v3&utm_medium=api_v3_business_search&utm_source=Vw2ZAYX48yvF8qP0CjwWnw", "review_count": 521, "categories": [{"alias": "bbq", "title": "Barbeque"}, {"alias": "comfortfood", "title": "Comfort Food"}, {"alias": "southern", "title": "Southern"}], "rating": 3.5, "coordinates": {"latitude": 40.731511, "longitude": -73.899936}, "transactions": ["pickup", "delivery"], "price": "$$", "location": {"address1": "5275 65th Pl", "address2": "", "address3": "", "city": "Maspeth", "zip_code": "11378", "country": "US", "state": "NY", "display_address": ["5275 65th Pl", "Maspeth, NY 11378"]}, "phone": "+17185650565", "display_phone": "(718) 565-0565", "distance": 7347.865880077197}, {"id": "WaeTm5dn16d99mkuKBCPZg", "alias": "printers-alley-new-york", "name": "Printers Alley", "image_url": "https://s3-media2.fl.yelpcdn.com/bphoto/8ajSMfxbRqZer1vfrV-jMw/o.jpg", "is_closed": false, "url": "https://www.yelp.com/biz/printers-alley-new-york?adjust_creative=Vw2ZAYX48yvF8qP0CjwWnw&utm_campaign=yelp_api_v3&utm_medium=api_v3_business_search&utm_source=Vw2ZAYX48yvF8qP0CjwWnw", "review_count": 75, "categories": [{"alias": "southern", "title": "Southern"}, {"alias": "sportsbars", "title": "Sports Bars"}, {"alias": "musicvenues", "title": "Music Venues"}], "rating": 3.5, "coordinates": {"latitude": 40.7552, "longitude": -73.9887}, "transactions": [], "price": "$$", "location": {"address1": "215 W 40th St", "address2": null, "address3": "", "city": "New York", "zip_code": "10018", "country": "US", "state": "NY", "display_address": ["215 W 40th St", "New York, NY 10018"]}, "phone": "+12124192770", "display_phone": "(212) 419-2770", "distance": 1010.7151237537951}, {"id": "_LF3ULe-5TI92CTJcWEz5g", "alias": "south-house-bar-and-restaurant-jersey-city", "name": "South House Bar & Restaurant", "image_url": "https://s3-media4.fl.yelpcdn.com/bphoto/1iJZ9pEh0fxByIcMKK7_IQ/o.jpg", "is_closed": false, "url": "https://www.yelp.com/biz/south-house-bar-and-restaurant-jersey-city?adjust_creative=Vw2ZAYX48yvF8qP0CjwWnw&utm_campaign=yelp_api_v3&utm_medium=api_v3_business_search&utm_source=Vw2ZAYX48yvF8qP0CjwWnw", "review_count": 558, "categories": [{"alias": "southern", "title": "Southern"}, {"alias": "cocktailbars", "title": "Cocktail Bars"}, {"alias": "musicvenues", "title": "Music Venues"}], "rating": 3.5, "coordinates": {"latitude": 40.7202578, "longitude": -74.0443068}, "transactions": [], "price": "$$", "location": {"address1": "149 Newark Ave", "address2": "", "address3": "", "city": "Jersey City", "zip_code": "07302", "country": "US", "state": "NJ", "display_address": ["149 Newark Ave", "Jersey City, NJ 07302"]}, "phone": "+12012091316", "display_phone": "(201) 209-1316", "distance": 7104.805681385524}, {"id": "mmFEdsr3os5z86aVP7tW0w", "alias": "tchoup-shop-brooklyn", "name": "Tchoup Shop", "image_url": "https://s3-media1.fl.yelpcdn.com/bphoto/yjNMYKoPM6TVIrx4FGv2iw/o.jpg", "is_closed": false, "url": "https://www.yelp.com/biz/tchoup-shop-brooklyn?adjust_creative=Vw2ZAYX48yvF8qP0CjwWnw&utm_campaign=yelp_api_v3&utm_medium=api_v3_business_search&utm_source=Vw2ZAYX48yvF8qP0CjwWnw", "review_count": 222, "categories": [{"alias": "cajun", "title": "Cajun/Creole"}, {"alias": "southern", "title": "Southern"}], "rating": 4.0, "coordinates": {"latitude": 40.70565, "longitude": -73.92161}, "transactions": ["pickup", "delivery"], "price": "$$", "location": {"address1": "50 Wyckoff Ave", "address2": "", "address3": "", "city": "Brooklyn", "zip_code": "11237", "country": "US", "state": "NY", "display_address": ["50 Wyckoff Ave", "Brooklyn, NY 11237"]}, "phone": "+19292343500", "display_phone": "(929) 234-3500", "distance": 7734.280807327839}, {"id": "FCms-eFFxnpMLm09AJridQ", "alias": "peaches-shrimp-and-crab-brooklyn-4", "name": "Peaches Shrimp and Crab", "image_url": "https://s3-media4.fl.yelpcdn.com/bphoto/6p6TD0rsb7TM6u22iQe03g/o.jpg", "is_closed": false, "url": "https://www.yelp.com/biz/peaches-shrimp-and-crab-brooklyn-4?adjust_creative=Vw2ZAYX48yvF8qP0CjwWnw&utm_campaign=yelp_api_v3&utm_medium=api_v3_business_search&utm_source=Vw2ZAYX48yvF8qP0CjwWnw", "review_count": 243, "categories": [{"alias": "seafood", "title": "Seafood"}, {"alias": "newamerican", "title": "American (New)"}, {"alias": "southern", "title": "Southern"}], "rating": 4.0, "coordinates": {"latitude": 40.6879838, "longitude": -73.9625478}, "transactions": ["pickup", "delivery"], "price": "$$", "location": {"address1": "285 Grand Ave", "address2": "", "address3": null, "city": "Brooklyn", "zip_code": "11238", "country": "US", "state": "NY", "display_address": ["285 Grand Ave", "Brooklyn, NY 11238"]}, "phone": "+17186389500", "display_phone": "(718) 638-9500", "distance": 8136.555242783704}, {"id": "WAeMNLzT8-0QncgsyVzZ9w", "alias": "art-bird-and-whiskey-bar-new-york", "name": "Art Bird & Whiskey Bar", "image_url": "https://s3-media4.fl.yelpcdn.com/bphoto/h30E6yK2pLX82HQrF08CCg/o.jpg", "is_closed": false, "url": "https://www.yelp.com/biz/art-bird-and-whiskey-bar-new-york?adjust_creative=Vw2ZAYX48yvF8qP0CjwWnw&utm_campaign=yelp_api_v3&utm_medium=api_v3_business_search&utm_source=Vw2ZAYX48yvF8qP0CjwWnw", "review_count": 79, "categories": [{"alias": "cocktailbars", "title": "Cocktail Bars"}, {"alias": "southern", "title": "Southern"}], "rating": 3.0, "coordinates": {"latitude": 40.7524183, "longitude": -73.977933}, "transactions": [], "location": {"address1": "89 E 42nd St", "address2": "Lower Level Dining Concourse", "address3": null, "city": "New York", "zip_code": "10017", "country": "US", "state": "NY", "display_address": ["89 E 42nd St", "Lower Level Dining Concourse", "New York, NY 10017"]}, "phone": "+12123402583", "display_phone": "(212) 340-2583", "distance": 839.3301623276659}, {"id": "fZ8RiMqZsTKqfr4RoSLBOQ", "alias": "sam-a-m-jersey-city-3", "name": "sam a.m.", "image_url": "https://s3-media2.fl.yelpcdn.com/bphoto/MqzmMW8DTk7oGDafmkTTIQ/o.jpg", "is_closed": false, "url": "https://www.yelp.com/biz/sam-a-m-jersey-city-3?adjust_creative=Vw2ZAYX48yvF8qP0CjwWnw&utm_campaign=yelp_api_v3&utm_medium=api_v3_business_search&utm_source=Vw2ZAYX48yvF8qP0CjwWnw", "review_count": 97, "categories": [{"alias": "newamerican", "title": "American (New)"}, {"alias": "southern", "title": "Southern"}, {"alias": "tradamerican", "title": "American (Traditional)"}], "rating": 4.5, "coordinates": {"latitude": 40.71015, "longitude": -74.06142}, "transactions": ["pickup", "delivery"], "price": "$$$$", "location": {"address1": "196 Pine St", "address2": null, "address3": "", "city": "Jersey City", "zip_code": "07304", "country": "US", "state": "NJ", "display_address": ["196 Pine St", "Jersey City, NJ 07304"]}, "phone": "+12014322304", "display_phone": "(201) 432-2304", "distance": 8932.896317174527}, {"id": "bjdcbfWWLLG2QnSm_cZ1aw", "alias": "bobwhite-counter-new-york-5", "name": "BobWhite Counter", "image_url": "https://s3-media4.fl.yelpcdn.com/bphoto/xZhcMCwjVwPy4fBEmBIJyw/o.jpg", "is_closed": false, "url": "https://www.yelp.com/biz/bobwhite-counter-new-york-5?adjust_creative=Vw2ZAYX48yvF8qP0CjwWnw&utm_campaign=yelp_api_v3&utm_medium=api_v3_business_search&utm_source=Vw2ZAYX48yvF8qP0CjwWnw", "review_count": 22, "categories": [{"alias": "southern", "title": "Southern"}, {"alias": "chickenshop", "title": "Chicken Shop"}, {"alias": "comfortfood", "title": "Comfort Food"}], "rating": 3.5, "coordinates": {"latitude": 40.75686, "longitude": -73.97228}, "transactions": [], "price": "$", "location": {"address1": "570 Lexington Ave", "address2": "", "address3": null, "city": "New York", "zip_code": "10022", "country": "US", "state": "NY", "display_address": ["570 Lexington Ave", "New York, NY 10022"]}, "phone": "", "display_phone": "", "distance": 602.2467240449026}, {"id": "yK2ZNKB2PBNty6R7prJCFA", "alias": "brooklyn-moon-cafe-brooklyn", "name": "Brooklyn Moon Cafe", "image_url": "https://s3-media1.fl.yelpcdn.com/bphoto/P0JsGBu9HiEZw35ptFJjgA/o.jpg", "is_closed": false, "url": "https://www.yelp.com/biz/brooklyn-moon-cafe-brooklyn?adjust_creative=Vw2ZAYX48yvF8qP0CjwWnw&utm_campaign=yelp_api_v3&utm_medium=api_v3_business_search&utm_source=Vw2ZAYX48yvF8qP0CjwWnw", "review_count": 319, "categories": [{"alias": "southern", "title": "Southern"}, {"alias": "newamerican", "title": "American (New)"}, {"alias": "caribbean", "title": "Caribbean"}], "rating": 3.5, "coordinates": {"latitude": 40.68662, "longitude": -73.97485}, "transactions": [], "price": "$$", "location": {"address1": "745 Fulton St", "address2": "", "address3": "", "city": "Brooklyn", "zip_code": "11217", "country": "US", "state": "NY", "display_address": ["745 Fulton St", "Brooklyn, NY 11217"]}, "phone": "+17188557149", "display_phone": "(718) 855-7149", "distance": 8183.846407501507}, {"id": "ueVSTErmXbqtN1glQd5p5A", "alias": "greedy-pot-new-york", "name": "Greedy Pot", "image_url": "https://s3-media3.fl.yelpcdn.com/bphoto/Tt1dWRZSxK6ZGisZGCBPlQ/o.jpg", "is_closed": false, "url": "https://www.yelp.com/biz/greedy-pot-new-york?adjust_creative=Vw2ZAYX48yvF8qP0CjwWnw&utm_campaign=yelp_api_v3&utm_medium=api_v3_business_search&utm_source=Vw2ZAYX48yvF8qP0CjwWnw", "review_count": 11, "categories": [{"alias": "caribbean", "title": "Caribbean"}, {"alias": "southern", "title": "Southern"}], "rating": 4.5, "coordinates": {"latitude": 40.80417, "longitude": -73.95216}, "transactions": ["delivery"], "location": {"address1": "1944 7th Ave", "address2": null, "address3": "", "city": "New York", "zip_code": "10026", "country": "US", "state": "NY", "display_address": ["1944 7th Ave", "New York, NY 10026"]}, "phone": "+19176757676", "display_phone": "(917) 675-7676", "distance": 5367.588882472021}, {"id": "htoLLZW9bvNlxWfMFa9kEA", "alias": "napoleons-southern-cuisine-and-bakery-brooklyn", "name": "Napoleon's Southern Cuisine & Bakery", "image_url": "https://s3-media1.fl.yelpcdn.com/bphoto/4MiDkloCViqWqUX8dE9uXg/o.jpg", "is_closed": false, "url": "https://www.yelp.com/biz/napoleons-southern-cuisine-and-bakery-brooklyn?adjust_creative=Vw2ZAYX48yvF8qP0CjwWnw&utm_campaign=yelp_api_v3&utm_medium=api_v3_business_search&utm_source=Vw2ZAYX48yvF8qP0CjwWnw", "review_count": 137, "categories": [{"alias": "bakeries", "title": "Bakeries"}, {"alias": "southern", "title": "Southern"}], "rating": 4.0, "coordinates": {"latitude": 40.68382, "longitude": -73.95416}, "transactions": ["pickup", "delivery"], "price": "$$", "location": {"address1": "1180 Bedford Ave", "address2": "", "address3": "", "city": "Brooklyn", "zip_code": "11216", "country": "US", "state": "NY", "display_address": ["1180 Bedford Ave", "Brooklyn, NY 11216"]}, "phone": "+13476633069", "display_phone": "(347) 663-3069", "distance": 8744.909020477147}, {"id": "unePwYAUWb7oC8RBt84e3A", "alias": "biyou-brooklyn", "name": "Biyou", "image_url": "https://s3-media3.fl.yelpcdn.com/bphoto/6whCODNJsdOW8X19EnCCTA/o.jpg", "is_closed": false, "url": "https://www.yelp.com/biz/biyou-brooklyn?adjust_creative=Vw2ZAYX48yvF8qP0CjwWnw&utm_campaign=yelp_api_v3&utm_medium=api_v3_business_search&utm_source=Vw2ZAYX48yvF8qP0CjwWnw", "review_count": 62, "categories": [{"alias": "cajun", "title": "Cajun/Creole"}, {"alias": "southern", "title": "Southern"}], "rating": 4.5, "coordinates": {"latitude": 40.68983, "longitude": -73.93656}, "transactions": ["pickup", "delivery"], "price": "$$", "location": {"address1": "198 Lewis Ave", "address2": null, "address3": "", "city": "Brooklyn", "zip_code": "11221", "country": "US", "state": "NY", "display_address": ["198 Lewis Ave", "Brooklyn, NY 11221"]}, "phone": "+17189287555", "display_phone": "(718) 928-7555", "distance": 8578.32842471526}, {"id": "QKVOdHaw54-DmYB9Dw2LOg", "alias": "parish-new-york-new-york", "name": "Parish New York", "image_url": "https://s3-media2.fl.yelpcdn.com/bphoto/-kwB7N2FQBhEiOJ8ilgEsw/o.jpg", "is_closed": false, "url": "https://www.yelp.com/biz/parish-new-york-new-york?adjust_creative=Vw2ZAYX48yvF8qP0CjwWnw&utm_campaign=yelp_api_v3&utm_medium=api_v3_business_search&utm_source=Vw2ZAYX48yvF8qP0CjwWnw", "review_count": 12, "categories": [{"alias": "cajun", "title": "Cajun/Creole"}, {"alias": "southern", "title": "Southern"}, {"alias": "bars", "title": "Bars"}], "rating": 4.0, "coordinates": {"latitude": 40.72057, "longitude": -73.98887}, "transactions": ["pickup", "delivery"], "location": {"address1": "146 Orchard St", "address2": null, "address3": "", "city": "New York", "zip_code": "10002", "country": "US", "state": "NY", "display_address": ["146 Orchard St", "New York, NY 10002"]}, "phone": "+12127060050", "display_phone": "(212) 706-0050", "distance": 4498.458001963641}, {"id": "YV0_CaPcvKKWhS9U4myBNA", "alias": "bobwhite-new-york-2", "name": "BobWhite", "image_url": "https://s3-media4.fl.yelpcdn.com/bphoto/7LGhym01sQmN-caP2rqx9A/o.jpg", "is_closed": false, "url": "https://www.yelp.com/biz/bobwhite-new-york-2?adjust_creative=Vw2ZAYX48yvF8qP0CjwWnw&utm_campaign=yelp_api_v3&utm_medium=api_v3_business_search&utm_source=Vw2ZAYX48yvF8qP0CjwWnw", "review_count": 8, "categories": [{"alias": "southern", "title": "Southern"}, {"alias": "comfortfood", "title": "Comfort Food"}], "rating": 4.5, "coordinates": {"latitude": 40.7542692566364, "longitude": -73.9766231486392}, "transactions": [], "location": {"address1": "230 Park Ave", "address2": "", "address3": null, "city": "New York", "zip_code": "10169", "country": "US", "state": "NY", "display_address": ["230 Park Ave", "New York, NY 10169"]}, "phone": "", "display_phone": "", "distance": 679.7702381296648}, {"id": "GZ7VNxJ4uOQiUbImz5gcjA", "alias": "johnny-kaks-international-new-york-4", "name": "Johnny Kaks International", "image_url": "https://s3-media4.fl.yelpcdn.com/bphoto/cyOZa68jMVpJnYnxHYoZtw/o.jpg", "is_closed": false, "url": "https://www.yelp.com/biz/johnny-kaks-international-new-york-4?adjust_creative=Vw2ZAYX48yvF8qP0CjwWnw&utm_campaign=yelp_api_v3&utm_medium=api_v3_business_search&utm_source=Vw2ZAYX48yvF8qP0CjwWnw", "review_count": 24, "categories": [{"alias": "caribbean", "title": "Caribbean"}, {"alias": "southern", "title": "Southern"}, {"alias": "soulfood", "title": "Soul Food"}], "rating": 4.5, "coordinates": {"latitude": 40.8200857, "longitude": -73.9399063}, "transactions": ["pickup", "delivery"], "price": "$", "location": {"address1": "2455 Adam Clayton Powell Blvd", "address2": null, "address3": "", "city": "New York", "zip_code": "10030", "country": "US", "state": "NY", "display_address": ["2455 Adam Clayton Powell Blvd", "New York, NY 10030"]}, "phone": "+12122341156", "display_phone": "(212) 234-1156", "distance": 7420.526764701203}, {"id": "oQGtOYCCp3QGGXfA6y5jzw", "alias": "texas-star-new-york", "name": "Texas Star", "image_url": "https://s3-media1.fl.yelpcdn.com/bphoto/K2Qbhd64e_muuzYHyMTfvg/o.jpg", "is_closed": false, "url": "https://www.yelp.com/biz/texas-star-new-york?adjust_creative=Vw2ZAYX48yvF8qP0CjwWnw&utm_campaign=yelp_api_v3&utm_medium=api_v3_business_search&utm_source=Vw2ZAYX48yvF8qP0CjwWnw", "review_count": 31, "categories": [{"alias": "southern", "title": "Southern"}, {"alias": "sandwiches", "title": "Sandwiches"}], "rating": 4.5, "coordinates": {"latitude": 40.825565, "longitude": -73.943893}, "transactions": [], "price": "$", "location": {"address1": "741 Saint Nicholas Ave", "address2": "", "address3": "", "city": "New York", "zip_code": "10031", "country": "US", "state": "NY", "display_address": ["741 Saint Nicholas Ave", "New York, NY 10031"]}, "phone": "+12129260133", "display_phone": "(212) 926-0133", "distance": 7829.533201075961}, {"id": "yIFI6afTRP-tBhY6WsUOPg", "alias": "popina-brooklyn", "name": "Popina", "image_url": "https://s3-media2.fl.yelpcdn.com/bphoto/0fXgXSGZUDU5lJTXA_rjgg/o.jpg", "is_closed": false, "url": "https://www.yelp.com/biz/popina-brooklyn?adjust_creative=Vw2ZAYX48yvF8qP0CjwWnw&utm_campaign=yelp_api_v3&utm_medium=api_v3_business_search&utm_source=Vw2ZAYX48yvF8qP0CjwWnw", "review_count": 38, "categories": [{"alias": "southern", "title": "Southern"}, {"alias": "italian", "title": "Italian"}], "rating": 4.5, "coordinates": {"latitude": 40.687361962701, "longitude": -74.0014251909241}, "transactions": [], "price": "$$", "location": {"address1": "127 Columbia St", "address2": "", "address3": null, "city": "Brooklyn", "zip_code": "11231", "country": "US", "state": "NY", "display_address": ["127 Columbia St", "Brooklyn, NY 11231"]}, "phone": "+17182221901", "display_phone": "(718) 222-1901", "distance": 8328.040867641355}, {"id": "6ezrABEThm48qv1qj8_FVw", "alias": "javelina-new-york-3", "name": "Javelina", "image_url": "https://s3-media1.fl.yelpcdn.com/bphoto/CJ2nQ8_C29Lme_ufKmFwPA/o.jpg", "is_closed": false, "url": "https://www.yelp.com/biz/javelina-new-york-3?adjust_creative=Vw2ZAYX48yvF8qP0CjwWnw&utm_campaign=yelp_api_v3&utm_medium=api_v3_business_search&utm_source=Vw2ZAYX48yvF8qP0CjwWnw", "review_count": 81, "categories": [{"alias": "tex-mex", "title": "Tex-Mex"}, {"alias": "mexican", "title": "Mexican"}, {"alias": "southern", "title": "Southern"}], "rating": 3.5, "coordinates": {"latitude": 40.7694, "longitude": -73.95816}, "transactions": ["pickup", "delivery"], "price": "$$", "location": {"address1": "1395 2nd Ave", "address2": "", "address3": null, "city": "New York", "zip_code": "10021", "country": "US", "state": "NY", "display_address": ["1395 2nd Ave", "New York, NY 10021"]}, "phone": "+19172617011", "display_phone": "(917) 261-7011", "distance": 1985.6955392235632}, {"id": "dPAjV-Yf-LCtYw5yRgLQWA", "alias": "crown-fried-chicken-new-york-7", "name": "Crown Fried Chicken", "image_url": "https://s3-media1.fl.yelpcdn.com/bphoto/5_Cn8tsogNykiilJ5pRzPw/o.jpg", "is_closed": false, "url": "https://www.yelp.com/biz/crown-fried-chicken-new-york-7?adjust_creative=Vw2ZAYX48yvF8qP0CjwWnw&utm_campaign=yelp_api_v3&utm_medium=api_v3_business_search&utm_source=Vw2ZAYX48yvF8qP0CjwWnw", "review_count": 10, "categories": [{"alias": "southern", "title": "Southern"}], "rating": 3.5, "coordinates": {"latitude": 40.81876, "longitude": -73.95263}, "transactions": [], "price": "$", "location": {"address1": "1514 Amsterdam Ave", "address2": "", "address3": "", "city": "New York", "zip_code": "10031", "country": "US", "state": "NY", "display_address": ["1514 Amsterdam Ave", "New York, NY 10031"]}, "phone": "", "display_phone": "", "distance": 6864.191154394748}, {"id": "xOYP9X_oTq7fqqy7NL1oVg", "alias": "big-easy-restaurant-jersey-city-2", "name": "Big Easy Restaurant", "image_url": "https://s3-media2.fl.yelpcdn.com/bphoto/0hfiJPcvykL3POiNxlHF9Q/o.jpg", "is_closed": false, "url": "https://www.yelp.com/biz/big-easy-restaurant-jersey-city-2?adjust_creative=Vw2ZAYX48yvF8qP0CjwWnw&utm_campaign=yelp_api_v3&utm_medium=api_v3_business_search&utm_source=Vw2ZAYX48yvF8qP0CjwWnw", "review_count": 72, "categories": [{"alias": "seafood", "title": "Seafood"}, {"alias": "cajun", "title": "Cajun/Creole"}, {"alias": "southern", "title": "Southern"}], "rating": 3.5, "coordinates": {"latitude": 40.71825, "longitude": -74.07458}, "transactions": ["pickup", "delivery"], "price": "$$", "location": {"address1": "640 Communipaw Ave", "address2": "", "address3": "", "city": "Jersey City", "zip_code": "07304", "country": "US", "state": "NJ", "display_address": ["640 Communipaw Ave", "Jersey City, NJ 07304"]}, "phone": "+12013333535", "display_phone": "(201) 333-3535", "distance": 9322.260400405348}, {"id": "JMUc5N8zswGvVv6t24wgyw", "alias": "brothers-seafood-new-york", "name": "Brothers Seafood", "image_url": "https://s3-media1.fl.yelpcdn.com/bphoto/tufxiCdnShqUEgavjyGLxw/o.jpg", "is_closed": false, "url": "https://www.yelp.com/biz/brothers-seafood-new-york?adjust_creative=Vw2ZAYX48yvF8qP0CjwWnw&utm_campaign=yelp_api_v3&utm_medium=api_v3_business_search&utm_source=Vw2ZAYX48yvF8qP0CjwWnw", "review_count": 28, "categories": [{"alias": "seafood", "title": "Seafood"}, {"alias": "soulfood", "title": "Soul Food"}, {"alias": "southern", "title": "Southern"}], "rating": 3.5, "coordinates": {"latitude": 40.8212890625, "longitude": -73.9273147583008}, "transactions": ["pickup", "delivery"], "price": "$", "location": {"address1": "632 Walton Ave", "address2": "", "address3": "", "city": "New York", "zip_code": "10451", "country": "US", "state": "NY", "display_address": ["632 Walton Ave", "New York, NY 10451"]}, "phone": "+13476661021", "display_phone": "(347) 666-1021", "distance": 8042.866543452162}, {"id": "HCO0K_4-p8fYxzD-kwFrWA", "alias": "johnsons-bbq-bronx", "name": "Johnson's BBQ", "image_url": "https://s3-media3.fl.yelpcdn.com/bphoto/VQM3i-VoGonG_7PaI3e_Gg/o.jpg", "is_closed": false, "url": "https://www.yelp.com/biz/johnsons-bbq-bronx?adjust_creative=Vw2ZAYX48yvF8qP0CjwWnw&utm_campaign=yelp_api_v3&utm_medium=api_v3_business_search&utm_source=Vw2ZAYX48yvF8qP0CjwWnw", "review_count": 29, "categories": [{"alias": "bbq", "title": "Barbeque"}, {"alias": "southern", "title": "Southern"}], "rating": 3.5, "coordinates": {"latitude": 40.8223876953125, "longitude": -73.902717590332}, "transactions": [], "price": "$$", "location": {"address1": "790 E 163rd St", "address2": null, "address3": "", "city": "Bronx", "zip_code": "10456", "country": "US", "state": "NY", "display_address": ["790 E 163rd St", "Bronx, NY 10456"]}, "phone": "+19144396187", "display_phone": "(914) 439-6187", "distance": 9408.982510139225}, {"id": "SsPZif4CIL85s318kxL7vA", "alias": "ashland-brooklyn", "name": "Ashland", "image_url": "https://s3-media1.fl.yelpcdn.com/bphoto/Vue9tBFL0mdw18ruP1XpWA/o.jpg", "is_closed": false, "url": "https://www.yelp.com/biz/ashland-brooklyn?adjust_creative=Vw2ZAYX48yvF8qP0CjwWnw&utm_campaign=yelp_api_v3&utm_medium=api_v3_business_search&utm_source=Vw2ZAYX48yvF8qP0CjwWnw", "review_count": 7, "categories": [{"alias": "southern", "title": "Southern"}, {"alias": "newamerican", "title": "American (New)"}], "rating": 4.5, "coordinates": {"latitude": 40.6958, "longitude": -73.98378}, "transactions": [], "location": {"address1": "156 Tilary St", "address2": null, "address3": "", "city": "Brooklyn", "zip_code": "11201", "country": "US", "state": "NY", "display_address": ["156 Tilary St", "Brooklyn, NY 11201"]}, "phone": "+17188758800", "display_phone": "(718) 875-8800", "distance": 7194.356393954484}, {"id": "BUlrIcNw0bzlKmvBP5SG5A", "alias": "vanel-on-first-new-york", "name": "Vanel on First", "image_url": "https://s3-media2.fl.yelpcdn.com/bphoto/toxULvftgIwlyyG3sMfJ7Q/o.jpg", "is_closed": false, "url": "https://www.yelp.com/biz/vanel-on-first-new-york?adjust_creative=Vw2ZAYX48yvF8qP0CjwWnw&utm_campaign=yelp_api_v3&utm_medium=api_v3_business_search&utm_source=Vw2ZAYX48yvF8qP0CjwWnw", "review_count": 3, "categories": [{"alias": "southern", "title": "Southern"}], "rating": 3.0, "coordinates": {"latitude": 40.726413, "longitude": -73.986579}, "transactions": [], "price": "$$", "location": {"address1": "95 First Ave", "address2": null, "address3": "", "city": "New York", "zip_code": "10003", "country": "US", "state": "NY", "display_address": ["95 First Ave", "New York, NY 10003"]}, "phone": "+12125333511", "display_phone": "(212) 533-3511", "distance": 3825.768379920634}, {"id": "Si3QKpqMLMK8CcUvT8YdLA", "alias": "bbq-pit-new-york", "name": "BBQ Pit", "image_url": "", "is_closed": false, "url": "https://www.yelp.com/biz/bbq-pit-new-york?adjust_creative=Vw2ZAYX48yvF8qP0CjwWnw&utm_campaign=yelp_api_v3&utm_medium=api_v3_business_search&utm_source=Vw2ZAYX48yvF8qP0CjwWnw", "review_count": 14, "categories": [{"alias": "bbq", "title": "Barbeque"}, {"alias": "southern", "title": "Southern"}], "rating": 1.5, "coordinates": {"latitude": 40.7385, "longitude": -73.98193}, "transactions": [], "price": "$$", "location": {"address1": "221 E 23rd St", "address2": "", "address3": "", "city": "New York", "zip_code": "10010", "country": "US", "state": "NY", "display_address": ["221 E 23rd St", "New York, NY 10010"]}, "phone": "+12126790700", "display_phone": "(212) 679-0700", "distance": 2427.219023535241}, {"id": "A4eHvtajTTEMPG0wB4ESWQ", "alias": "deriks-open-flame-new-york", "name": "Derik's Open Flame", "image_url": "https://s3-media1.fl.yelpcdn.com/bphoto/rNmtlgJKb8-x2qtJfK-jbQ/o.jpg", "is_closed": false, "url": "https://www.yelp.com/biz/deriks-open-flame-new-york?adjust_creative=Vw2ZAYX48yvF8qP0CjwWnw&utm_campaign=yelp_api_v3&utm_medium=api_v3_business_search&utm_source=Vw2ZAYX48yvF8qP0CjwWnw", "review_count": 3, "categories": [{"alias": "bbq", "title": "Barbeque"}, {"alias": "southern", "title": "Southern"}], "rating": 2.5, "coordinates": {"latitude": 40.73847, "longitude": -73.98071}, "transactions": ["pickup", "delivery"], "location": {"address1": "413 2nd Ave", "address2": "", "address3": "", "city": "New York", "zip_code": "10010", "country": "US", "state": "NY", "display_address": ["413 2nd Ave", "New York, NY 10010"]}, "phone": "+12127254422", "display_phone": "(212) 725-4422", "distance": 2422.4535589080137}, {"id": "5rdbKdbm9wGa9-xiC0O51A", "alias": "crown-fried-chicken-new-york-13", "name": "Crown Fried Chicken", "image_url": "https://s3-media1.fl.yelpcdn.com/bphoto/K9A0M9zC0XQIADagFsY0kw/o.jpg", "is_closed": false, "url": "https://www.yelp.com/biz/crown-fried-chicken-new-york-13?adjust_creative=Vw2ZAYX48yvF8qP0CjwWnw&utm_campaign=yelp_api_v3&utm_medium=api_v3_business_search&utm_source=Vw2ZAYX48yvF8qP0CjwWnw", "review_count": 6, "categories": [{"alias": "southern", "title": "Southern"}, {"alias": "seafood", "title": "Seafood"}, {"alias": "burgers", "title": "Burgers"}], "rating": 3.0, "coordinates": {"latitude": 40.82951, "longitude": -73.94853}, "transactions": [], "location": {"address1": "3633 Broadway", "address2": "", "address3": "", "city": "New York", "zip_code": "10031", "country": "US", "state": "NY", "display_address": ["3633 Broadway", "New York, NY 10031"]}, "phone": "+12124917288", "display_phone": "(212) 491-7288", "distance": 8103.540286955201}, {"id": "5_9jnbe_izc3l9tbG_QdvA", "alias": "ghost-truck-kitchen-jersey-city", "name": "Ghost Truck Kitchen", "image_url": "https://s3-media1.fl.yelpcdn.com/bphoto/cDaFPM9ipo21MOHEAFIgGA/o.jpg", "is_closed": false, "url": "https://www.yelp.com/biz/ghost-truck-kitchen-jersey-city?adjust_creative=Vw2ZAYX48yvF8qP0CjwWnw&utm_campaign=yelp_api_v3&utm_medium=api_v3_business_search&utm_source=Vw2ZAYX48yvF8qP0CjwWnw", "review_count": 2, "categories": [{"alias": "southern", "title": "Southern"}, {"alias": "asianfusion", "title": "Asian Fusion"}, {"alias": "tradamerican", "title": "American (Traditional)"}], "rating": 5.0, "coordinates": {"latitude": 40.7209, "longitude": -74.04809}, "transactions": [], "location": {"address1": "356 Varick St", "address2": null, "address3": "", "city": "Jersey City", "zip_code": "07302", "country": "US", "state": "NJ", "display_address": ["356 Varick St", "Jersey City, NJ 07302"]}, "phone": "+12017063989", "display_phone": "(201) 706-3989", "distance": 7315.626901623883}, {"id": "GgVSxkEzFRyAorxuODA1tQ", "alias": "masala-indian-cuisine-jersey-city", "name": "Masala Indian Cuisine", "image_url": "", "is_closed": false, "url": "https://www.yelp.com/biz/masala-indian-cuisine-jersey-city?adjust_creative=Vw2ZAYX48yvF8qP0CjwWnw&utm_campaign=yelp_api_v3&utm_medium=api_v3_business_search&utm_source=Vw2ZAYX48yvF8qP0CjwWnw", "review_count": 2, "categories": [{"alias": "indpak", "title": "Indian"}, {"alias": "southern", "title": "Southern"}, {"alias": "vegetarian", "title": "Vegetarian"}], "rating": 1.0, "coordinates": {"latitude": 40.7353, "longitude": -74.06465}, "transactions": ["pickup", "delivery"], "location": {"address1": "789 Newark Ave", "address2": null, "address3": "", "city": "Jersey City", "zip_code": "07306", "country": "US", "state": "NJ", "display_address": ["789 Newark Ave", "Jersey City, NJ 07306"]}, "phone": "+12012229512", "display_phone": "(201) 222-9512", "distance": 7769.627669969632}, {"id": "VnMer6ETcmJbMdVbGNmwTg", "alias": "kennedys-bronx", "name": "Kennedy's", "image_url": "", "is_closed": false, "url": "https://www.yelp.com/biz/kennedys-bronx?adjust_creative=Vw2ZAYX48yvF8qP0CjwWnw&utm_campaign=yelp_api_v3&utm_medium=api_v3_business_search&utm_source=Vw2ZAYX48yvF8qP0CjwWnw", "review_count": 2, "categories": [{"alias": "sandwiches", "title": "Sandwiches"}, {"alias": "southern", "title": "Southern"}], "rating": 2.5, "coordinates": {"latitude": 40.830243568669, "longitude": -73.8916383683681}, "transactions": [], "location": {"address1": "1282 Southern Blvd", "address2": "", "address3": null, "city": "Bronx", "zip_code": "10459", "country": "US", "state": "NY", "display_address": ["1282 Southern Blvd", "Bronx, NY 10459"]}, "phone": "+13478621581", "display_phone": "(347) 862-1581", "distance": 10681.784175127488}]}